pytcpmqtt/__init__.py
pytcpmqtt/main.py
pytcpmqtt-1.3.1.dist-info/LICENCE
pytcpmqtt-1.3.1.dist-info/METADATA
pytcpmqtt-1.3.1.dist-info/WHEEL
pytcpmqtt-1.3.1.dist-info/top_level.txt
pytcpmqtt-1.3.1.dist-info/RECORD
