Metadata-Version: 2.1
Name: pytcpmqtt
Version: 1.3.1
Summary: Connexion TCP <-> MQTT ssl ou wss
Home-page: UNKNOWN
Author: Didier Orlandi
Author-email: didier.orlandi@wanadoo.fr
License: UNKNOWN
Platform: UNKNOWN
Classifier: Programming Language :: Python :: 3
Classifier: License :: OSI Approved :: MIT License
Classifier: Operating System :: OS Independent
Requires-Python: >=3.6
Requires-Dist: paho-mqtt
Requires-Dist: mqtt-thread
